voice.py
voice_python-0.2.0.dist-info/METADATA
voice_python-0.2.0.dist-info/WHEEL
voice_python-0.2.0.dist-info/licenses/LICENSE
voice_python-0.2.0.dist-info/RECORD
