Metadata-Version: 2.1
Name: voice-python
Version: 0.2.0
Summary: Python implementation of The vOICe (seeingwithsound.com).
Project-URL: Homepage, https://github.com/RuizSerra/vOICe-python
Project-URL: Bug Tracker, https://github.com/RuizSerra/vOICe-python/issues
Author-email: Jaime Ruiz Serra <jrs271828@gmail.com>
License: Copyright 2022 Jaime Ruiz Serra
Classifier: License :: OSI Approved :: MIT License
Classifier: Operating System :: OS Independent
Classifier: Programming Language :: Python :: 3
Requires-Python: >=3.7
Requires-Dist: numpy
Requires-Dist: opencv-python==4.5.5.64
